SocialCrawler/2test_sc_008.py
SocialCrawler/ExtractorData.py
SocialCrawler/HTTPResponseError.py
SocialCrawler/HackFoursquare.py
SocialCrawler/HeadLess.py
SocialCrawler/HistoricalCollector.py
SocialCrawler/NewExtractorData.py
SocialCrawler/__init__.py
SocialCrawler/test_ned.py
SocialCrawler/test_sc_008.py
SocialCrawler-0.4.1.dist-info/DESCRIPTION.rst
SocialCrawler-0.4.1.dist-info/METADATA
SocialCrawler-0.4.1.dist-info/RECORD
SocialCrawler-0.4.1.dist-info/WHEEL
SocialCrawler-0.4.1.dist-info/metadata.json
SocialCrawler-0.4.1.dist-info/top_level.txt
