Metadata-Version: 2.0
Name: SocialCrawler
Version: 0.4.1
Summary: This package allow you get data from Twitter, Swarm(check-ins) and Foursquare
Home-page: http://github.com/JosielWirlino/SocialCrawler
Author: J.Wirlino and A. Adativa
Author-email: josiel.wirlino@gmail.com, alice.adativa@gmail.com
License: GNU
Platform: UNKNOWN
Classifier: Intended Audience :: Developers
Classifier: Intended Audience :: Science/Research
Classifier: License :: OSI Approved :: GNU General Public License (GPL)
Classifier: Programming Language :: Python :: 3
Classifier: Programming Language :: Python :: 3.4
Classifier: Programming Language :: Python :: 3.5
Classifier: Topic :: Scientific/Engineering :: Information Analysis
Requires-Dist: colorama
Requires-Dist: pyvirtualdisplay
Requires-Dist: requests (>=2.4.3)
Requires-Dist: selenium
Requires-Dist: termcolor
Requires-Dist: tweepy
